MANIFEST.in
contact_view.xml
setup.py
./__init__.py
./__openerp__.py
./contact.py
i18n/bs.po
i18n/cs.po
i18n/de.po
i18n/es.po
i18n/fi.po
i18n/fr.po
i18n/he.po
i18n/hr.po
i18n/hu.po
i18n/lt.po
i18n/mk.po
i18n/nl.po
i18n/pl.po
i18n/portal_crm.pot
i18n/pt.po
i18n/pt_BR.po
i18n/ro.po
i18n/sl.po
i18n/sv.po
i18n/th.po
i18n/tr.po
i18n/zh_CN.po
openerp_portal_crm.egg-info/PKG-INFO
openerp_portal_crm.egg-info/SOURCES.txt
openerp_portal_crm.egg-info/dependency_links.txt
openerp_portal_crm.egg-info/requires.txt
openerp_portal_crm.egg-info/top_level.txt
test/contact_form.yml